Metadata-Version: 2.1
Name: qtsass310
Version: 0.3.1.post0
Summary: Compile SCSS files to valid Qt stylesheets.
Home-page: https://github.com/spyder-ide/qtsass
Author: Yann Lanthony
Maintainer: The Spyder Project Contributors
Maintainer-email: qtsass@spyder-ide.org
License: MIT
Keywords: qt sass qtsass scss css qss stylesheets
Classifier: Development Status :: 5 - Production/Stable
Classifier: Intended Audience :: Developers
Classifier: License :: OSI Approved :: MIT License
Classifier: Natural Language :: English
Classifier: Operating System :: OS Independent
Classifier: Programming Language :: Python
Classifier: Programming Language :: Python :: 3.7
Classifier: Programming Language :: Python :: 3.8
Classifier: Programming Language :: Python :: 3.9
Classifier: Programming Language :: Python :: 3.10
Classifier: Topic :: Software Development :: Build Tools
Classifier: Topic :: Software Development :: Libraries :: Python Modules
Requires-Python: >=3.7
License-File: LICENSE.txt
Requires-Dist: libsass
